LICENSE
MANIFEST.in
README.md
pytest_informative_node.py
setup.py
pytest_informative_node.egg-info/PKG-INFO
pytest_informative_node.egg-info/SOURCES.txt
pytest_informative_node.egg-info/dependency_links.txt
pytest_informative_node.egg-info/entry_points.txt
pytest_informative_node.egg-info/requires.txt
pytest_informative_node.egg-info/top_level.txt