Metadata-Version: 2.1
Name: pytest-informative-node
Version: 0.2.0
Summary: display more node ininformation.
Home-page: https://github.com/megachweng/pytest-informative-node
Author: megachweng
Author-email: megachweng@gmail.com
Maintainer: megachweng
Maintainer-email: megachweng@gmail.com
License: MIT
Platform: UNKNOWN
Classifier: Development Status :: 4 - Beta
Classifier: Framework :: Pytest
Classifier: Intended Audience :: Developers
Classifier: Topic :: Software Development :: Testing
Classifier: Programming Language :: Python :: 3.6
Classifier: Programming Language :: Python :: 3.7
Classifier: Programming Language :: Python :: Implementation :: CPython
Classifier: Operating System :: POSIX
Classifier: License :: OSI Approved :: MIT License
Requires-Python: >=2.7, !=3.0.*, !=3.1.*, !=3.2.*, !=3.3.*
